greenreactor.py
greenreactor-0.1.4.dist-info/LICENSE
greenreactor-0.1.4.dist-info/METADATA
greenreactor-0.1.4.dist-info/WHEEL
greenreactor-0.1.4.dist-info/top_level.txt
greenreactor-0.1.4.dist-info/RECORD
